cllu/__about__.py
cllu/__init__.py
cllu-0.0.1a0.dist-info/METADATA
cllu-0.0.1a0.dist-info/WHEEL
cllu-0.0.1a0.dist-info/licenses/LICENSE.txt
cllu-0.0.1a0.dist-info/RECORD
