Metadata-Version: 2.1
Name: cllu
Version: 0.0.1a0
Project-URL: Documentation, https://github.com/unknown/cllu#readme
Project-URL: Issues, https://github.com/unknown/cllu/issues
Project-URL: Source, https://github.com/unknown/cllu
Author-email: Robert Luce <rbobluce@gmail.com>
License-Expression: MIT
License-File: LICENSE.txt
Classifier: Development Status :: 1 - Planning
Classifier: Programming Language :: Python
Classifier: Programming Language :: Python :: 3.7
Classifier: Programming Language :: Python :: 3.8
Classifier: Programming Language :: Python :: 3.9
Classifier: Programming Language :: Python :: 3.10
Classifier: Programming Language :: Python :: 3.11
Classifier: Programming Language :: Python :: Implementation :: CPython
Classifier: Programming Language :: Python :: Implementation :: PyPy
Requires-Python: >=3.7
